tca_beam/__init__.py
tca_beam/config.py
tca_beam/helpers.py
tca_beam/run.py
tca_beam/settings.py
tca_beam/tca_beam.py
tca_beam/template_rendering.py
tca_beam/templates/.beam-settings.toml
tca_beam/templates/AllPreviews.swift
tca_beam/templates/OneFile.swift
tca_beam/templates/TwoFile_ReducerPart.swift
tca_beam/templates/TwoFile_ViewPart.swift
tca_beam/templates/View.swift
tca_beam/templates/ViewFeature.swift
tca_beam-0.7.0.dist-info/WHEEL
tca_beam-0.7.0.dist-info/entry_points.txt
tca_beam-0.7.0.dist-info/METADATA
tca_beam-0.7.0.dist-info/RECORD
