Metadata-Version: 2.1
Name: tca-beam
Version: 0.7.0
Summary: Feature stub generation for The Composable Architecture
Author: Alex Hunsley
Author-email: alex.hunsley@gmail.com
Requires-Python: >=3.7,<4.0
Classifier: Programming Language :: Python :: 3
Classifier: Programming Language :: Python :: 3.7
Classifier: Programming Language :: Python :: 3.8
Classifier: Programming Language :: Python :: 3.9
Classifier: Programming Language :: Python :: 3.10
Classifier: Programming Language :: Python :: 3.11
Requires-Dist: click (>=8.1.3,<9.0.0)
Requires-Dist: jinja2 (>=3.1.2,<4.0.0)
